scoopy/__init__.py
scoopy/base.py
scoopy/data_sources.py
scoopy/util.py
scoopy/examples/__init__.py
scoopy/examples/search_and_save_news.py
scoopy-0.0.6.dist-info/LICENSE
scoopy-0.0.6.dist-info/METADATA
scoopy-0.0.6.dist-info/WHEEL
scoopy-0.0.6.dist-info/top_level.txt
scoopy-0.0.6.dist-info/RECORD
