Metadata-Version: 2.1
Name: scoopy
Version: 0.0.6
Summary: Python interface to live news
Home-page: https://github.com/thorwhalen/scoopy
Author: Thor Whalen
License: mit
Platform: any
License-File: LICENSE
Requires-Dist: dol
Requires-Dist: argh
Requires-Dist: requests
